Workbook

Sheet niaz
B2: Name: Shuchita Faruque Shirsha
B3: FINAL PART A
A13: Monthly Budget
A14: January 2022 – June 2022
A15: Expence Catagori's | B15: jan | C15: feb | D15: mar | E15: apr | F15: may | G15: jun | H15: avg | I15: total
A16: House Payment | B16: 4400 | C16: 4401 | D16: 4402 | E16: 4403 | F16: 4404 | G16: 4405 | H16: =AVERAGE(B16:G16) -> 4402.5 | I16: 4407
A17: Gasoline | B17: 5050 | C17: 5051 | D17: 5052 | E17: 5053 | F17: 5054 | G17: 5055 | H17: =AVERAGE(B17:G17) -> 5052.5 | I17: =SUM(B17:G17) -> 30315
A18: Groceries | B18: 3500 | C18: 3500 | D18: 3500 | E18: 3500 | F18: 3500 | G18: 3500 | H18: =AVERAGE(B18:G18) -> 3500 | I18: =SUM(B18:G18) -> 21000
A19: Utilities | B19: 1500 | C19: 1501 | D19: 1502 | E19: 1503 | F19: 1504 | G19: 1505 | H19: =AVERAGE(B19:G19) -> 1502.5 | I19: =SUM(B19:G19) -> 9015
A20: Insurance | B20: 20000 | C20: 20000 | D20: 20000 | E20: 20000 | F20: 20000 | G20: 20000 | H20: =AVERAGE(B20:G20) -> 20000 | I20: =SUM(B20:G20) -> 120000
A21: Entertainment | B21: 10000 | C21: 10000 | D21: 10000 | E21: 10000 | F21: 10000 | G21: 10000 | H21: =AVERAGE(B21:G21) -> 10000 | I21: =SUM(B21:G21) -> 60000
A22: Other | B22: 7589 | C22: 7590 | D22: 7591 | E22: 7592 | F22: 7593 | G22: 7594 | H22: =AVERAGE(B22:G22) -> 7591.5 | I22: =SUM(B22:G22) -> 45549
A23: Monthly Expenses Total | B23: =SUM(B16:B22) -> 52039 | C23: =SUM(C16:C22) -> 52043 | D23: =SUM(D16:D22) -> 52047 | E23: =SUM(E16:E22) -> 52051 | F23: =SUM(F16:F22) -> 52055 | G23: =SUM(G16:G22) -> 52059
A25: Income | B25: 20000 | C25: 21000 | D25: 27000 | E25: 19000 | F25: 25000 | G25: 29000

Sheet hasan
A1: Category | B1: Total (Jan-Jun) | D1: Month | E1: Expenses | F1: Income
A2: House Payment | B2: =niaz!I16 -> 4407 | D2: January | E2: =niaz!B23 -> 52039 | F2: =niaz!B25 -> 20000
A3: Gasoline | B3: =niaz!I17 -> 30315 | D3: February | E3: =niaz!C23 -> 52043 | F3: =niaz!C25 -> 21000
A4: Groceries | B4: =niaz!I18 -> 21000 | D4: March | E4: =niaz!D23 -> 52047 | F4: =niaz!D25 -> 27000
A5: Utilities | B5: =niaz!I19 -> 9015 | D5: April | E5: =niaz!E23 -> 52051 | F5: =niaz!E25 -> 19000
A6: Insurance | B6: =niaz!I20 -> 120000 | D6: May | E6: =niaz!F23 -> 52055 | F6: =niaz!F25 -> 25000
A7: Entertainment | B7: =niaz!I21 -> 60000 | D7: June | E7: =niaz!G23 -> 52059 | F7: =niaz!G25 -> 29000
A8: Other | B8: =niaz!I22 -> 45549
A10: Chart Date: | B10: December 12, 2025
